mpl_modernqt/__init__.py
mpl_modernqt/backend.py
mpl_modernqt-1.3.dist-info/METADATA
mpl_modernqt-1.3.dist-info/WHEEL
mpl_modernqt-1.3.dist-info/licenses/LICENSE
mpl_modernqt-1.3.dist-info/RECORD
