Metadata-Version: 2.1
Name: mpl-modernqt
Version: 1.3
Summary: Modern Qt Matplotlib backend
Project-URL: Homepage, https://github.com/aloytag/mpl-modernqt
Project-URL: Bug Tracker, https://github.com/aloytag/mpl-modernqt/issues
Project-URL: Repository, https://github.com/aloytag/mpl-modernqt
Author-email: "Dr. Ing. Ariel S. Loyarte" <aloyarte@frsf.utn.edu.ar>
License: MIT
License-File: LICENSE
Keywords: backend,matplotlib,plotting
Classifier: License :: OSI Approved :: MIT License
Classifier: Operating System :: OS Independent
Classifier: Programming Language :: Python :: 3
Requires-Python: >=3.8
Requires-Dist: matplotlib>=3.6.0
Requires-Dist: pyqtdarktheme>=2.1.0
Requires-Dist: qtawesome>=1.2.2
